wandb_workspaces/__init__.py
wandb_workspaces/expr.py
wandb_workspaces/reports/__init__.py
wandb_workspaces/reports/v1/__init__.py
wandb_workspaces/reports/v1/_blocks.py
wandb_workspaces/reports/v1/_helpers.py
wandb_workspaces/reports/v1/_panels.py
wandb_workspaces/reports/v1/_templates.py
wandb_workspaces/reports/v1/blocks.py
wandb_workspaces/reports/v1/helpers.py
wandb_workspaces/reports/v1/mutations.py
wandb_workspaces/reports/v1/panels.py
wandb_workspaces/reports/v1/report.py
wandb_workspaces/reports/v1/runset.py
wandb_workspaces/reports/v1/templates.py
wandb_workspaces/reports/v1/util.py
wandb_workspaces/reports/v1/validators.py
wandb_workspaces/reports/v2/__init__.py
wandb_workspaces/reports/v2/blocks.py
wandb_workspaces/reports/v2/gql.py
wandb_workspaces/reports/v2/interface.py
wandb_workspaces/reports/v2/internal.py
wandb_workspaces/reports/v2/metrics.py
wandb_workspaces/reports/v2/panels.py
wandb_workspaces/utils/__init__.py
wandb_workspaces/utils/data_generation.py
wandb_workspaces/utils/invertable_dict.py
wandb_workspaces/utils/validators.py
wandb_workspaces/workspaces/__init__.py
wandb_workspaces/workspaces/errors.py
wandb_workspaces/workspaces/interface.py
wandb_workspaces/workspaces/internal.py
wandb_workspaces-0.3.3.dist-info/METADATA
wandb_workspaces-0.3.3.dist-info/WHEEL
wandb_workspaces-0.3.3.dist-info/licenses/LICENSE
wandb_workspaces-0.3.3.dist-info/RECORD
